oauth_provider/__init__.py
oauth_provider/admin.py
oauth_provider/apps.py
oauth_provider/models.py
oauth_provider/tests.py
oauth_provider/views.py
oauth_provider/migrations/__init__.py
django_oauth_provider-0.0.1.dev0.dist-info/LICENSE
django_oauth_provider-0.0.1.dev0.dist-info/METADATA
django_oauth_provider-0.0.1.dev0.dist-info/WHEEL
django_oauth_provider-0.0.1.dev0.dist-info/top_level.txt
django_oauth_provider-0.0.1.dev0.dist-info/RECORD
